{
 "total-stylesheets": 1,
 "total-stylesheet-size": 195435,
 "total-media-queries": 5,
 "media-queries": [
  "screen and (min-width:45em)",
  "screen and (min-width:64em)",
  "screen and (max-width:44.9375em)",
  "screen and (min-width:45em) and (max-width:63.9375em)",
  "screen and (max-width:63.9375em)"
 ],
 "total-rules": 241,
 "selectors-per-rule": 1.3195020746887967,
 "total-selectors": 318,
 "identifiers-per-selector": 1.2169811320754718,
 "specificity-per-selector": 8.89622641509434,
 "top-selector-specificity": 30,
 "top-selector-specificity-selector": ".o-expander-toggle[aria-expanded=true] .o-icon",
 "total-id-selectors": 0,
 "total-identifiers": 383,
 "total-declarations": 492,
 "total-unique-colours": 9,
 "unique-colours": [
  "#FFFF00",
  "#000000",
  "#333333",
  "#FFFFFF",
  "#7F7F7F",
  "#4C4C4C",
  "#CCCCCC",
  "#B2B2B2",
  "#D9D9D9"
 ],
 "total-important-keywords": 4
}